wifi/__init__.py
wifi/__main__.py
wifi/cli.py
wifi/exceptions.py
wifi/scan.py
wifi/scheme.py
wifi/subprocess_compat.py
wifi/utils.py
wifi_ap_force-1.0.3.dist-info/LICENSE
wifi_ap_force-1.0.3.dist-info/WHEEL
wifi_ap_force-1.0.3.dist-info/METADATA
wifi_ap_force-1.0.3.dist-info/RECORD
